ci/__init__.py
ci/admin.py
ci/context_processors.py
ci/forms.py
ci/models.py
ci/urls.py
ci/utils.py
ci/views.py
ci/management/__init__.py
ci/management/commands/__init__.py
ci/management/commands/generate_reports.py
ci/migrations/__init__.py
ci/static/ci/css/application.css
ci/static/ci/css/docs.css
ci/static/ci/css/font-awesome.min.css
ci/static/ci/css/jquery-confirm.css
ci/static/ci/css/sapphire-theme.css
ci/static/ci/css/sapphire.css
ci/static/ci/css/styles.css
ci/static/ci/css/toolkit-inverse.css
ci/static/ci/css/toolkit-light.css
ci/static/ci/fonts/FontAwesome.otf
ci/static/ci/fonts/fontawesome-webfont.eot
ci/static/ci/fonts/fontawesome-webfont.svg
ci/static/ci/fonts/fontawesome-webfont.ttf
ci/static/ci/fonts/fontawesome-webfont.woff
ci/static/ci/fonts/fontawesome-webfont.woff2
ci/static/ci/fonts/toolkit-entypo.eot
ci/static/ci/fonts/toolkit-entypo.ttf
ci/static/ci/fonts/toolkit-entypo.woff
ci/static/ci/fonts/toolkit-entypo.woff2
ci/static/ci/img/logo.png
ci/static/ci/js/application.js
ci/static/ci/js/chart.js
ci/static/ci/js/d3.v3.min.js
ci/static/ci/js/highcharts.js
ci/static/ci/js/jquery-confirm.js
ci/static/ci/js/jquery.min.js
ci/static/ci/js/sapphire.js
ci/static/ci/js/strain.js
ci/static/ci/js/superagent.js
ci/static/ci/js/tablesorter.min.js
ci/static/ci/js/toolkit.js
ci/templates/ci/base.html
ci/templates/ci/changes.html
ci/templates/ci/changes_detail.html
ci/templates/ci/dashboard.html
ci/templates/ci/denied.html
ci/templates/ci/failures_outbounds.html
ci/templates/ci/failures_schedules.html
ci/templates/ci/failures_subscriptions.html
ci/templates/ci/health_messages.html
ci/templates/ci/health_registrations.html
ci/templates/ci/health_subscriptions.html
ci/templates/ci/identities.html
ci/templates/ci/identities_detail.html
ci/templates/ci/index.html
ci/templates/ci/login.html
ci/templates/ci/not_found.html
ci/templates/ci/registrations.html
ci/templates/ci/registrations_detail.html
ci/templates/ci/reports.html
ci/templates/ci/services.html
seed_control_interface-0.9.18.dist-info/LICENCE
seed_control_interface-0.9.18.dist-info/METADATA
seed_control_interface-0.9.18.dist-info/WHEEL
seed_control_interface-0.9.18.dist-info/top_level.txt
seed_control_interface-0.9.18.dist-info/RECORD
