Metadata-Version: 2.1
Name: seed-control-interface
Version: 0.9.18
Summary: Seed Scheduler mircoservice
Home-page: http://github.com/praekelt/seed-control-interface
Author: Praekelt.org
Author-email: dev@praekelt.org
License: BSD
Platform: UNKNOWN
Classifier: Development Status :: 4 - Beta
Classifier: Framework :: Django
Classifier: License :: OSI Approved :: BSD License
Classifier: Programming Language :: Python
Classifier: Programming Language :: Python :: 2.7
Classifier: Topic :: Software Development :: Libraries :: Python Modules
Requires-Dist: Django (==2.2.8)
Requires-Dist: dj-database-url (==0.3.0)
Requires-Dist: psycopg2 (==2.7.1)
Requires-Dist: raven (==5.32.0)
Requires-Dist: whitenoise (==2.0.6)
Requires-Dist: pytz (==2015.7)
Requires-Dist: python-dateutil (==2.5.3)
Requires-Dist: django-bootstrap-form (==3.2.1)
Requires-Dist: seed-services-client (==0.37.2)
Requires-Dist: openpyxl (==2.4.0)
Requires-Dist: attrs (==19.1.0)
Requires-Dist: django-bootstrap-datepicker (==1.2.2)
Requires-Dist: URLObject (<3.0,>=2.4.3)
